{
  "type": "FeatureCollection",
  "features": [
    {
      "type": "Feature",
      "properties": {
        "id": "03e5d1d6-bea1-4ff3-9b47-4b4a811da01b",
        "homespotname": "Tobis"
      },
      "geometry": {
        "coordinates": [
          [
            [
              12.107838688101737,
              49.02197031393723
            ],
            [
              12.107754112544773,
              49.02196758929086
            ],
            [
              12.107670351524222,
              49.02195944159247
            ],
            [
              12.107588211730993,
              49.021945949311494
            ],
            [
              12.10750848424062,
              49.021927242390255
            ],
            [
              12.107431936893832,
              49.02190350099239
            ],
            [
              12.107359306900985,
              49.021874953767544
            ],
            [
              12.107291293741671,
              49.0218418756491
            ],
            [
              12.107228552427834,
              49.02180458520615
            ],
            [
              12.107171687195335,
              49.02176344157505
            ],
            [
              12.107121245684734,
              49.0217188410005
            ],
            [
              12.107077713667314,
              49.021671213019104
            ],
            [
              12.107041510367141,
              49.021621016322364
            ],
            [
              12.107012984424223,
              49.02156873433893
            ],
            [
              12.106992410537572,
              49.02151487057865
            ],
            [
              12.106979986820543,
              49.02145994378325
            ],
            [
              12.106975832893824,
              49.021404482930436
            ],
            [
              12.106979988734434,
              49.021349022139425
            ],
            [
              12.106992414291804,
              49.021294095527075
            ],
            [
              12.107012989874523,
              49.02124023206404
            ],
            [
              12.107041517304058,
              49.02118795048062
            ],
            [
              12.107077721824265,
              49.02113775427132
            ],
            [
              12.107121254748252,
              49.02109012684604
            ],
            [
              12.107171696817115,
              49.02104552687489
            ],
            [
              12.107228562238117,
              49.02100438387132
            ],
            [
              12.107291303363453,
              49.0209670940559
            ],
            [
              12.107359315964505,
              49.02093401654088
            ],
            [
              12.107431945050783,
              49.02090546987214
            ],
            [
              12.107508491177537,
              49.020881728961704
            ],
            [
              12.107588217181293,
              49.02086302244049
            ],
            [
              12.107670355278453,
              49.02084953045675
            ],
            [
              12.107754114458666,
              49.02084138294141
            ],
            [
              12.107838688101737,
              49.02083865835686
            ],
            [
              12.107923261744805,
              49.02084138294141
            ],
            [
              12.108007020925017,
              49.02084953045675
            ],
            [
              12.108089159022178,
              49.02086302244049
            ],
            [
              12.108168885025934,
              49.020881728961704
            ],
            [
              12.108245431152687,
              49.02090546987214
            ],
            [
              12.108318060238966,
              49.02093401654088
            ],
            [
              12.108386072840016,
              49.0209670940559
            ],
            [
              12.108448813965355,
              49.02100438387132
            ],
            [
              12.108505679386354,
              49.02104552687489
            ],
            [
              12.108556121455218,
              49.02109012684604
            ],
            [
              12.108599654379205,
              49.02113775427132
            ],
            [
              12.108635858899412,
              49.02118795048062
            ],
            [
              12.108664386328947,
              49.02124023206404
            ],
            [
              12.108684961911665,
              49.021294095527075
            ],
            [
              12.108697387469036,
              49.021349022139425
            ],
            [
              12.10870154330965,
              49.021404482930436
            ],
            [
              12.108697389382927,
              49.02145994378325
            ],
            [
              12.108684965665898,
              49.02151487057865
            ],
            [
              12.108664391779246,
              49.02156873433893
            ],
            [
              12.108635865836328,
              49.021621016322364
            ],
            [
              12.108599662536156,
              49.021671213019104
            ],
            [
              12.108556130518739,
              49.0217188410005
            ],
            [
              12.108505689008135,
              49.02176344157505
            ],
            [
              12.108448823775635,
              49.02180458520615
            ],
            [
              12.108386082461799,
              49.0218418756491
            ],
            [
              12.108318069302484,
              49.021874953767544
            ],
            [
              12.108245439309638,
              49.02190350099239
            ],
            [
              12.10816889196285,
              49.021927242390255
            ],
            [
              12.108089164472476,
              49.021945949311494
            ],
            [
              12.10800702467925,
              49.02195944159247
            ],
            [
              12.107923263658696,
              49.02196758929086
            ],
            [
              12.107838688101737,
              49.02197031393723
            ]
          ]
        ],
        "type": "Polygon"
      },
      "id": 1
    }
  ]
}